mongodb_cloud_helper/__init__.py
mongodb_cloud_helper/bp/__init__.py
mongodb_cloud_helper/bp/mongo_local_connector.py
mongodb_cloud_helper/bp/mongo_srv_connector.py
mongodb_cloud_helper/mongo_base_api.py
mongodb_cloud_helper/svc/__init__.py
mongodb_cloud_helper/svc/find_documents.py
mongodb_cloud_helper/svc/find_documents_by_query.py
mongodb_cloud_helper/svc/persist_documents.py
mongodb_cloud_helper-0.1.6.dist-info/WHEEL
mongodb_cloud_helper-0.1.6.dist-info/METADATA
mongodb_cloud_helper-0.1.6.dist-info/RECORD
